pipeweave/__init__.py
pipeweave/cli.py
pipeweave/core.py
pipeweave/dashboard/__init__.py
pipeweave/stage.py
pipeweave/step.py
pipeweave/storage/__init__.py
pipeweave/storage/base.py
pipeweave/storage/sqlite.py
pipeweave-0.4.1.dist-info/LICENSE
pipeweave-0.4.1.dist-info/METADATA
pipeweave-0.4.1.dist-info/WHEEL
pipeweave-0.4.1.dist-info/RECORD
