Metadata-Version: 2.3
Name: pipeweave
Version: 0.4.1
Summary: A flexible Python data pipeline library using finite state machines for custom data processing workflows
License: MIT
Keywords: pipeline,data,fsm,workflow
Author: Taylor Tyler
Author-email: taylorgtyler@gmail.com
Requires-Python: >=3.11,<4.0
Classifier: Development Status :: 3 - Alpha
Classifier: Intended Audience :: Developers
Classifier: License :: OSI Approved :: MIT License
Classifier: Programming Language :: Python :: 3
Classifier: Programming Language :: Python :: 3.11
Classifier: Programming Language :: Python :: 3.12
Classifier: Programming Language :: Python :: 3.13
Requires-Dist: pyyaml (>=6.0.2,<7.0.0)
Requires-Dist: streamlit (>=1.40.0,<2.0.0)
Project-URL: Documentation, https://github.com/taylorgtyler/pipeweave
Project-URL: Homepage, https://github.com/taylorgtyler/pipeweave
Project-URL: Repository, https://github.com/taylorgtyler/pipeweave
